[
    {
        "key": "datr",
        "value": "kz9IZwvO7UwfGCzGrQnXCwcx",
        "domain": "facebook.com",
        "path": "/",
        "hostOnly": false,
        "creation": "2025-06-05T09:03:51.393Z",
        "lastAccessed": "2025-06-05T09:03:51.393Z"
    },
    {
        "key": "sb",
        "value": "kz9IZ-GCcxDiOVHovildaTa8",
        "domain": "facebook.com",
        "path": "/",
        "hostOnly": false,
        "creation": "2025-06-05T09:03:51.393Z",
        "lastAccessed": "2025-06-05T09:03:51.393Z"
    },
    {
        "key": "ps_l",
        "value": "1",
        "domain": "facebook.com",
        "path": "/",
        "hostOnly": false,
        "creation": "2025-06-05T09:03:51.393Z",
        "lastAccessed": "2025-06-05T09:03:51.393Z"
    },
    {
        "key": "ps_n",
        "value": "1",
        "domain": "facebook.com",
        "path": "/",
        "hostOnly": false,
        "creation": "2025-06-05T09:03:51.393Z",
        "lastAccessed": "2025-06-05T09:03:51.393Z"
    },
    {
        "key": "dpr",
        "value": "0.8999999761581421",
        "domain": "facebook.com",
        "path": "/",
        "hostOnly": false,
        "creation": "2025-06-05T09:03:51.393Z",
        "lastAccessed": "2025-06-05T09:03:51.393Z"
    },
    {
        "key": "locale",
        "value": "en_US",
        "domain": "facebook.com",
        "path": "/",
        "hostOnly": false,
        "creation": "2025-06-05T09:03:51.393Z",
        "lastAccessed": "2025-06-05T09:03:51.393Z"
    },
    {
        "key": "c_user",
        "value": "100063770418147",
        "domain": "facebook.com",
        "path": "/",
        "hostOnly": false,
        "creation": "2025-06-05T09:03:51.393Z",
        "lastAccessed": "2025-06-05T09:03:51.393Z"
    },
    {
        "key": "fr",
        "value": "1qGGWOkLBWksj574u.AWe5XChf9XpZKPiN2l9JBNxf1T8uEDeyihq1ii59sB81Uf5gE6o.BoQV15..AAA.0.0.BoQV15.AWeEBcaGBCuAw3IvzErp3h0DDFw",
        "domain": "facebook.com",
        "path": "/",
        "hostOnly": false,
        "creation": "2025-06-05T09:03:51.393Z",
        "lastAccessed": "2025-06-05T09:03:51.393Z"
    },
    {
        "key": "xs",
        "value": "24%3AQv38r8kpLuGAcg%3A2%3A1749059660%3A-1%3A-1%3A%3AAcWM2TV0GikM2Lnh6gsxHmxow8uDbMdZtM6vpS0d0A",
        "domain": "facebook.com",
        "path": "/",
        "hostOnly": false,
        "creation": "2025-06-05T09:03:51.393Z",
        "lastAccessed": "2025-06-05T09:03:51.393Z"
    },
    {
        "key": "wd",
        "value": "1777x812",
        "domain": "facebook.com",
        "path": "/",
        "hostOnly": false,
        "creation": "2025-06-05T09:03:51.393Z",
        "lastAccessed": "2025-06-05T09:03:51.393Z"
    },
    {
        "key": "presence",
        "value": "C%7B%22t3%22%3A%5B%5D%2C%22utc3%22%3A1749114229234%2C%22v%22%3A1%7D",
        "domain": "facebook.com",
        "path": "/",
        "hostOnly": false,
        "creation": "2025-06-05T09:03:51.393Z",
        "lastAccessed": "2025-06-05T09:03:51.393Z"
    }
]
